{"skeleton":{"hash":"oyqMFTz07wSQ751+ECINR/Bv9vc","spine":"3.8.99","x":-46.5,"y":-46.39,"width":93,"height":92.62,"images":"./images/","audio":"D:/Project/Minigames/Animation"},"bones":[{"name":"root"},{"name":"boneCoinPosition","parent":"root"},{"name":"boneCoin","parent":"boneCoinPosition","color":"ff0000ff"},{"name":"boneCoinSide","parent":"boneCoinPosition","color":"599ae8ff"},{"name":"boneCoinSpin","parent":"boneCoinPosition","color":"0b478fff"},{"name":"boneBack","parent":"boneCoinPosition","color":"ff0000ff"},{"name":"boneFXPosition","parent":"root","color":"eeff17ff"},{"name":"boneStart1","parent":"boneFXPosition"},{"name":"boneFlare","parent":"boneFXPosition"},{"name":"boneRing","parent":"boneFXPosition"},{"name":"boneStart2","parent":"boneFXPosition"},{"name":"boneStart3","parent":"boneFXPosition"},{"name":"boneStart4","parent":"boneFXPosition"},{"name":"boneStart5","parent":"boneFXPosition"},{"name":"boneStart6","parent":"boneFXPosition"},{"name":"boneStart7","parent":"boneFXPosition"},{"name":"boneStart8","parent":"boneFXPosition"},{"name":"boneStart9","parent":"boneFXPosition"},{"name":"boneStart10","parent":"boneFXPosition"},{"name":"boneStart11","parent":"boneFXPosition"},{"name":"boneRing2","parent":"boneFXPosition"},{"name":"boneLight","parent":"boneFXPosition","x":-100,"color":"ffec0bff"}],"slots":[{"name":"coinSpin","bone":"boneCoinSpin","attachment":"coinSpin"},{"name":"coinSide","bone":"boneCoinSide","attachment":"coinSide"},{"name":"coinBack","bone":"boneBack","attachment":"coinBack"},{"name":"fxRing","bone":"boneRing"},{"name":"fxRing2","bone":"boneRing2"},{"name":"fxFlare","bone":"boneFlare"},{"name":"fxStart","bone":"boneStart1"},{"name":"fxStart2","bone":"boneStart2"},{"name":"fxStart3","bone":"boneStart3"},{"name":"fxStart4","bone":"boneStart4"},{"name":"fxStart5","bone":"boneStart5"},{"name":"fxStart6","bone":"boneStart6"},{"name":"fxStart7","bone":"boneStart7"},{"name":"fxStart8","bone":"boneStart8"},{"name":"fxStart9","bone":"boneStart9"},{"name":"fxStart10","bone":"boneStart10"},{"name":"fxStart11","bone":"boneStart11"},{"name":"coinFront","bone":"boneCoin","attachment":"coinFront"},{"name":"boneLight","bone":"boneCoin","attachment":"boneLight"},{"name":"fxLight","bone":"boneLight","color":"fff5a8ff","attachment":"fxLight","blend":"additive"}],"skins":[{"name":"default","attachments":{"boneLight":{"boneLight":{"type":"clipping","end":"boneLight","vertexCount":35,"vertices":[-0.17,46.23,-7.48,45.35,-16.45,42.76,-25.57,38.05,-33.78,31.06,-40.31,21.94,-43.54,14.42,-45.33,6.82,-45.93,0.12,-45.47,-7.83,-42.94,-15.94,-39.56,-23.38,-34.99,-29.63,-29.25,-35.04,-23,-39.6,-15.56,-42.82,-8.63,-45.18,0.16,-45.69,8.27,-45.52,17.73,-42.65,25.85,-38.93,31.76,-33.52,37.37,-27.13,41.02,-21.66,44.17,-14.19,46.16,-7.38,46.33,-0.24,46.19,5.02,44.39,13.22,41.27,21.58,35.53,29.78,29.79,35.85,20.12,41.75,12.74,44.7,6.51,46.02],"color":"ce3a3aff"}},"coinBack":{"coinBack":{"width":93,"height":92}},"coinFront":{"coinFront":{"y":-0.39,"width":93,"height":92}},"coinSide":{"coinSide":{"width":18,"height":92}},"coinSpin":{"coinSpin":{"width":92,"height":92}},"fxFlare":{"fxFlare":{"width":108,"height":108}},"fxLight":{"fxLight":{"rotation":-45,"width":88,"height":275}},"fxRing":{"fxRing":{"scaleX":1.006,"scaleY":1.006,"width":108,"height":108}},"fxRing2":{"fxRing":{"scaleX":1.006,"scaleY":1.006,"width":108,"height":108}},"fxStart":{"fxStart":{"width":54,"height":54}},"fxStart2":{"fxStart":{"width":54,"height":54}},"fxStart3":{"fxStart":{"width":54,"height":54}},"fxStart4":{"fxStart":{"width":54,"height":54}},"fxStart5":{"fxStart":{"width":54,"height":54}},"fxStart6":{"fxStart":{"width":54,"height":54}},"fxStart7":{"fxStart":{"width":54,"height":54}},"fxStart8":{"fxStart":{"width":54,"height":54}},"fxStart9":{"fxStart":{"width":54,"height":54}},"fxStart10":{"fxStart":{"width":54,"height":54}},"fxStart11":{"fxStart":{"width":54,"height":54}}}}],"animations":{"Collect":{"slots":{"coinBack":{"attachment":[{"name":null}]},"coinFront":{"color":[{"color":"ffffffff","curve":0.25,"c3":0.75},{"time":0.0333,"color":"ffffff00"}],"attachment":[{"time":0.3333,"name":null}]},"coinSide":{"attachment":[{"name":null}]},"coinSpin":{"attachment":[{"name":null}]},"fxFlare":{"color":[{"color":"ffffffff","curve":0.25,"c3":0.75},{"time":0.3333,"color":"ffffff00"}],"attachment":[{"name":"fxFlare"}]},"fxRing":{"color":[{"color":"ffffffff","curve":0.25,"c3":0.75},{"time":0.3333,"color":"ffffff00"}],"attachment":[{"name":"fxRing"}]},"fxRing2":{"color":[{"color":"ffffff7f","curve":0.375,"c2":0.5,"c3":0.75},{"time":0.1667,"color":"ffffffff","curve":0.25,"c3":0.75},{"time":0.5,"color":"ffffff00"}],"attachment":[{"name":"fxRing"}]},"fxStart":{"color":[{"color":"ffffff7f","curve":0.375,"c2":0.5,"c3":0.75},{"time":0.1667,"color":"ffffffff","curve":0.25,"c3":0.75},{"time":0.6667,"color":"ffffff00"}],"attachment":[{"name":"fxStart"}]},"fxStart2":{"color":[{"color":"ffffff00","curve":0.25,"c3":0.75},{"time":0.3333,"color":"ffffffff","curve":0.25,"c3":0.75},{"time":0.8333,"color":"ffffff00"}],"attachment":[{"name":"fxStart"}]},"fxStart3":{"color":[{"color":"ffffff7f","curve":0.375,"c2":0.5,"c3":0.75},{"time":0.1667,"color":"ffffffff","curve":0.25,"c3":0.75},{"time":0.6667,"color":"ffffff00"}],"attachment":[{"name":"fxStart"}]},"fxStart4":{"color":[{"color":"ffffff00","curve":"stepped"},{"time":0.1667,"color":"ffffff00","curve":0.25,"c3":0.75},{"time":0.5,"color":"ffffffff","curve":0.25,"c3":0.75},{"time":1,"color":"ffffff00"}],"attachment":[{"name":"fxStart"}]},"fxStart5":{"color":[{"color":"ffffff00","curve":0.32,"c2":0.29,"c3":0.757},{"time":0.6667,"color":"ffffff00"}],"attachment":[{"name":"fxStart"}]},"fxStart6":{"color":[{"color":"ffffff00","curve":0.25,"c3":0.75},{"time":0.3333,"color":"ffffffff","curve":0.25,"c3":0.75},{"time":0.8333,"color":"ffffff00"}],"attachment":[{"name":"fxStart"}]},"fxStart7":{"color":[{"color":"ffffff00","curve":0.32,"c2":0.29,"c3":0.757},{"time":0.6667,"color":"ffffff00"}],"attachment":[{"name":"fxStart"}]},"fxStart8":{"color":[{"color":"ffffff00","curve":"stepped"},{"time":0.1667,"color":"ffffff00","curve":0.25,"c3":0.75},{"time":0.5,"color":"ffffffff","curve":0.25,"c3":0.75},{"time":1,"color":"ffffff00"}],"attachment":[{"name":"fxStart"}]},"fxStart9":{"color":[{"color":"ffffff7f","curve":0.375,"c2":0.5,"c3":0.75},{"time":0.1667,"color":"ffffffff","curve":0.25,"c3":0.75},{"time":0.6667,"color":"ffffff00"}],"attachment":[{"name":"fxStart"}]},"fxStart10":{"color":[{"color":"ffffff00","curve":0.25,"c3":0.75},{"time":0.3333,"color":"ffffffff","curve":0.25,"c3":0.75},{"time":0.8333,"color":"ffffff00"}],"attachment":[{"name":"fxStart"}]},"fxStart11":{"color":[{"color":"ffffff7f","curve":0.375,"c2":0.5,"c3":0.75},{"time":0.1667,"color":"ffffffff","curve":0.25,"c3":0.75},{"time":0.6667,"color":"ffffff00"}],"attachment":[{"name":"fxStart"}]}},"bones":{"boneRing":{"scale":[{"curve":0.25,"c3":0.75},{"time":0.3333,"x":1.836,"y":1.836}]},"boneStart1":{"rotate":[{"angle":-12.77,"curve":0.32,"c2":0.29,"c3":0.757},{"time":0.6667,"angle":-98.15}],"translate":[{"x":3.09,"y":14.63,"curve":0.32,"c2":0.29,"c3":0.757},{"time":0.6667,"x":23.76,"y":112.46}],"scale":[{"x":0.924,"y":0.924,"curve":0.32,"c2":0.29,"c3":0.757},{"time":0.6667,"x":0.418,"y":0.418}]},"boneStart2":{"rotate":[{"curve":0.25,"c3":0.75},{"time":0.8333,"angle":-98.15}],"translate":[{"curve":0.25,"c3":0.75},{"time":0.8333,"x":-55.03,"y":110.22}],"scale":[{"curve":0.25,"c3":0.75},{"time":0.8333,"x":0.418,"y":0.418}]},"boneStart3":{"rotate":[{"angle":-12.77,"curve":0.32,"c2":0.29,"c3":0.757},{"time":0.6667,"angle":-98.15}],"translate":[{"x":-16.21,"y":-2.67,"curve":0.32,"c2":0.29,"c3":0.757},{"time":0.6667,"x":-124.57,"y":-20.51}],"scale":[{"x":0.924,"y":0.924,"curve":0.32,"c2":0.29,"c3":0.757},{"time":0.6667,"x":0.418,"y":0.418}]},"boneStart4":{"rotate":[{"time":0.1667,"curve":0.25,"c3":0.75},{"time":1,"angle":-98.15}],"translate":[{"time":0.1667,"curve":0.25,"c3":0.75},{"time":1,"x":-46.82,"y":-33.58}],"scale":[{"time":0.1667,"curve":0.25,"c3":0.75},{"time":1,"x":0.418,"y":0.418}]},"boneStart5":{"rotate":[{"angle":-12.77,"curve":0.32,"c2":0.29,"c3":0.757},{"time":0.6667,"angle":-98.15}],"translate":[{"x":-12.59,"y":-18.8,"curve":0.32,"c2":0.29,"c3":0.757},{"time":0.6667,"x":-96.75,"y":-144.47}],"scale":[{"x":0.924,"y":0.924,"curve":0.32,"c2":0.29,"c3":0.757},{"time":0.6667,"x":0.418,"y":0.418}]},"boneStart6":{"rotate":[{"curve":0.25,"c3":0.75},{"time":0.8333,"angle":-98.15}],"translate":[{"curve":0.25,"c3":0.75},{"time":0.8333,"x":138.15,"y":-65.89}],"scale":[{"curve":0.25,"c3":0.75},{"time":0.8333,"x":0.418,"y":0.418}]},"boneStart7":{"rotate":[{"angle":-12.77,"curve":0.32,"c2":0.29,"c3":0.757},{"time":0.6667,"angle":-98.15}],"translate":[{"x":8.69,"y":-16.09,"curve":0.32,"c2":0.29,"c3":0.757},{"time":0.6667,"x":66.81,"y":-123.7}],"scale":[{"x":0.924,"y":0.924,"curve":0.32,"c2":0.29,"c3":0.757},{"time":0.6667,"x":0.418,"y":0.418}]},"boneStart8":{"rotate":[{"time":0.1667,"curve":0.25,"c3":0.75},{"time":1,"angle":-98.15}],"translate":[{"time":0.1667,"curve":0.25,"c3":0.75},{"time":1,"x":111.09,"y":27.59}],"scale":[{"time":0.1667,"curve":0.25,"c3":0.75},{"time":1,"x":0.418,"y":0.418}]},"boneStart9":{"rotate":[{"angle":-12.77,"curve":0.32,"c2":0.29,"c3":0.757},{"time":0.6667,"angle":-98.15}],"translate":[{"x":10.61,"y":9.35,"curve":0.32,"c2":0.29,"c3":0.757},{"time":0.6667,"x":81.57,"y":71.87}],"scale":[{"x":0.924,"y":0.924,"curve":0.32,"c2":0.29,"c3":0.757},{"time":0.6667,"x":0.418,"y":0.418}]},"boneStart10":{"rotate":[{"curve":0.25,"c3":0.75},{"time":0.8333,"angle":-98.15}],"translate":[{"curve":0.25,"c3":0.75},{"time":0.8333,"x":-150.9,"y":66.95}],"scale":[{"curve":0.25,"c3":0.75},{"time":0.8333,"x":0.418,"y":0.418}]},"boneStart11":{"rotate":[{"angle":-12.77,"curve":0.32,"c2":0.29,"c3":0.757},{"time":0.6667,"angle":-98.15}],"translate":[{"x":6.29,"y":-4.57,"curve":0.32,"c2":0.29,"c3":0.757},{"time":0.6667,"x":48.36,"y":-35.14}],"scale":[{"x":0.924,"y":0.924,"curve":0.32,"c2":0.29,"c3":0.757},{"time":0.6667,"x":0.418,"y":0.418}]},"boneRing2":{"scale":[{"time":0.1667,"curve":0.25,"c3":0.75},{"time":0.5,"x":1.836,"y":1.836}]}}},"Spin":{"slots":{"coinBack":{"color":[{"color":"ffffff00","curve":"stepped"},{"time":0.6667,"color":"ffffff00","curve":0.25,"c3":0.75},{"time":0.7,"color":"ffffffff"}]},"coinFront":{"color":[{"time":0.6667,"color":"ffffffff","curve":0.25,"c3":0.75},{"time":0.7,"color":"ffffff00","curve":"stepped"},{"time":1.9667,"color":"ffffff00","curve":0.25,"c3":0.75},{"time":2,"color":"ffffffff"}]},"fxLight":{"color":[{"color":"f0ff6bbf"}]}},"bones":{"boneCoinSpin":{"translate":[{"curve":0.25,"c3":0.75},{"time":0.6667,"x":8,"curve":0.25,"c3":0.75},{"time":0.7,"x":-8,"curve":0.25,"c3":0.75},{"time":1.3333,"curve":0.25,"c3":0.75},{"time":2,"x":8,"curve":0.25,"c3":0.75},{"time":2.0333,"x":-8,"curve":0.25,"c3":0.75},{"time":2.6667}],"scale":[{"curve":0.25,"c3":0.75},{"time":0.6667,"x":0,"curve":"stepped"},{"time":0.7,"x":0,"curve":0.25,"c3":0.75},{"time":1.3333,"curve":0.25,"c3":0.75},{"time":2,"x":0,"curve":"stepped"},{"time":2.0333,"x":0,"curve":0.25,"c3":0.75},{"time":2.6667}]},"boneCoinSide":{"scale":[{"x":0,"curve":0.25,"c3":0.75},{"time":0.5,"x":0.9,"curve":0.25,"c3":0.75},{"time":0.6667,"curve":0.25,"c3":0.75},{"time":0.8333,"x":0.9,"curve":0.25,"c3":0.75},{"time":1.3333,"x":0,"curve":0.25,"c3":0.75},{"time":1.8333,"x":0.9,"curve":0.25,"c3":0.75},{"time":2,"curve":0.25,"c3":0.75},{"time":2.1667,"x":0.9,"curve":0.25,"c3":0.75},{"time":2.6667,"x":0}]},"boneCoin":{"translate":[{"curve":0.25,"c3":0.75},{"time":0.6667,"x":-8,"curve":0.25,"c3":0.75},{"time":1.3333,"curve":0.25,"c3":0.75},{"time":2,"x":8,"curve":0.25,"c3":0.75},{"time":2.6667}],"scale":[{"curve":0.25,"c3":0.75},{"time":0.6667,"x":0,"curve":0.25,"c3":0.75},{"time":1.3333,"curve":0.25,"c3":0.75},{"time":2,"x":0,"curve":0.25,"c3":0.75},{"time":2.6667}]},"boneBack":{"translate":[{"x":8,"curve":"stepped"},{"time":0.7,"x":8,"curve":0.25,"c3":0.75},{"time":1.3333,"curve":0.25,"c3":0.75},{"time":2,"x":-8}],"scale":[{"x":0,"curve":"stepped"},{"time":0.7,"x":0,"curve":0.25,"c3":0.75},{"time":1.3333,"curve":0.25,"c3":0.75},{"time":2,"x":0}]},"boneLight":{"translate":[{"curve":0.264,"c3":0.75},{"time":0.6667,"x":236.82}]}}}}}